pystylie/__init__.py
pystylie-2.8.dist-info/METADATA
pystylie-2.8.dist-info/WHEEL
pystylie-2.8.dist-info/top_level.txt
pystylie-2.8.dist-info/RECORD
